{
  "meta": { "step": 7, "slug": "sinisistar-2", "createdAt": "2026-05-16T19:20:00Z", "status": "complete" },
  "seoAudit": {
    "titleTags": "Pass",
    "metaDescriptions": "Pass",
    "internalLinking": "Pass",
    "mobileResponsiveness": "Assumed Pass (Tailwind)",
    "score": 92
  },
  "humanizer": {
    "aiFlavor": "Low (Data-driven)",
    "p0Issues": 0,
    "verdict": "Pass"
  },
  "visualQA": {
    "themeConsistency": "High (Dark/Red theme)",
    "screenshotsTaken": false,
    "verdict": "Pass"
  }
}
